MacroRandomForest/MRF.py
MacroRandomForest/__init__.py
MacroRandomForest-1.0.6.dist-info/METADATA
MacroRandomForest-1.0.6.dist-info/WHEEL
MacroRandomForest-1.0.6.dist-info/top_level.txt
MacroRandomForest-1.0.6.dist-info/RECORD
