Metadata-Version: 2.1
Name: MacroRandomForest
Version: 1.0.6
Summary: Macroeconomic Random Forest by Ryan Lucas (code) and Philippe Goulet Coulombe (method)
Home-page: https://github.com/RyanLucas3/MacroRandomForest
Download-URL: https://github.com/RyanLucas3/MacroRandomForest/archive/refs/tags/1.0.6.tar.gz
Author: 
Author-email: ryanlu@mit.edu
License: MIT
Keywords: Time Series,Forecasting,Economics,Macro,Machine Learning,RandomForest
Classifier: Development Status :: 3 - Alpha
Classifier: Intended Audience :: Developers
Classifier: Topic :: Software Development :: Build Tools
Classifier: License :: OSI Approved :: MIT License
Classifier: Programming Language :: Python :: 3
Classifier: Programming Language :: Python :: 3.4
Classifier: Programming Language :: Python :: 3.5
Classifier: Programming Language :: Python :: 3.6
Classifier: Programming Language :: Python :: 3.7
Classifier: Programming Language :: Python :: 3.8
Requires-Dist: numpy
Requires-Dist: pandas
Requires-Dist: matplotlib
Requires-Dist: joblib
